async_api_throttler/__init__.py
async_api_throttler/async_api_throttler.py
async_api_throttler/count_down.py
async_api_throttler/exceptions.py
async_api_throttler-0.2.0.dist-info/METADATA
async_api_throttler-0.2.0.dist-info/WHEEL
async_api_throttler-0.2.0.dist-info/top_level.txt
async_api_throttler-0.2.0.dist-info/RECORD
