Metadata-Version: 2.1
Name: async-api-throttler
Version: 0.2.0
Summary: Consume any API with no ratelimit breach, patient mode 💤
Home-page: https://github.com/devamin/async-api-throttler/
Author: Amine Benkhouya
Author-email: amine.benkhouya@example.com
License: MIT
Classifier: Programming Language :: Python :: 3
Classifier: License :: OSI Approved :: MIT License
Classifier: Operating System :: OS Independent
